LICENSE
MANIFEST.in
README.md
setup.py
tests/__init__.py
tests/http_response_catcher.py
tests/test_helper.py
tests/controllers/__init__.py
tests/controllers/controller_test_base.py
tests/controllers/test_api_controller.py
zjecfsdagl/__init__.py
zjecfsdagl/api_helper.py
zjecfsdagl/configuration.py
zjecfsdagl/decorators.py
zjecfsdagl/zjecfsdagl_client.py
zjecfsdagl.egg-info/PKG-INFO
zjecfsdagl.egg-info/SOURCES.txt
zjecfsdagl.egg-info/dependency_links.txt
zjecfsdagl.egg-info/requires.txt
zjecfsdagl.egg-info/top_level.txt
zjecfsdagl/controllers/__init__.py
zjecfsdagl/controllers/api_controller.py
zjecfsdagl/controllers/base_controller.py
zjecfsdagl/exceptions/__init__.py
zjecfsdagl/exceptions/api_exception.py
zjecfsdagl/http/__init__.py
zjecfsdagl/http/http_call_back.py
zjecfsdagl/http/http_client.py
zjecfsdagl/http/http_context.py
zjecfsdagl/http/http_method_enum.py
zjecfsdagl/http/http_request.py
zjecfsdagl/http/http_response.py
zjecfsdagl/http/requests_client.py
zjecfsdagl/http/auth/__init__.py
zjecfsdagl/http/auth/basic_auth.py
zjecfsdagl/models/__init__.py
zjecfsdagl/models/suite_code_enum.py